{
  "dogs": [
    {
      "name": "Estefania",
      "description": "This description was edited using the modify dog modal.",
      "image": "/assets/dalmation.png",
      "isFavorite": false,
      "id": 12
    },
    {
      "name": "Santiago",
      "image": "/assets/corgi.png",
      "description": "woman Global piercing Rap Web",
      "isFavorite": true,
      "id": 14
    },
    {
      "name": "Olivia",
      "description": "City Optimized Corporate Clothing Implemented Metal navigating Chair",
      "image": "/assets/cowardly.png",
      "isFavorite": true,
      "id": 15
    },
    {
      "name": "Anjali",
      "description": "This is a voluptuous dog!",
      "image": "/assets/dalmation.png",
      "isFavorite": false,
      "id": 16
    },
    {
      "name": "Helga",
      "image": "/assets/boxer.jpeg",
      "description": "She's Russian and she knows it.",
      "isFavorite": false,
      "id": 19
    },
    {
      "name": "Sammy",
      "description": "His name is long so I just wrote his nickname.",
      "image": "/assets/boxer.jpeg",
      "isFavorite": false,
      "id": 23
    },
    {
      "name": "Landen",
      "description": "He's kind of a player and a jerk.",
      "image": "/assets/boxer.jpeg",
      "isFavorite": false,
      "id": 25
    },
    {
      "name": "Severous",
      "description": "He's from Slitherine but he's still pretty awesome.",
      "image": "/assets/chihuahua.avif",
      "isFavorite": false,
      "id": 27
    },
    {
      "name": "Delilah",
      "description": "She is sweet! She has my favorite name of all the names. I love her!",
      "image": "/assets/cowardly.png",
      "isFavorite": true,
      "id": 28
    },
    {
      "name": "Scorpio",
      "description": "He doesn't have any special powers. He's kind of lame.",
      "image": "/assets/corgi.png",
      "isFavorite": true,
      "id": 29
    },
    {
      "name": "Qua-Keesha",
      "description": "Yes, the double alliteration was on purpose. We like the letter \"Q\".",
      "image": "/assets/dalmation.png",
      "isFavorite": false,
      "id": 30
    },
    {
      "name": "Yermom3000",
      "description": "This is an immature dog that doesn't know the line for 'your mom' jokes.",
      "image": "/assets/cowardly.png",
      "isFavorite": false,
      "id": 31
    },
    {
      "name": "Killian",
      "description": "This dog was named after a dead cat.",
      "image": "/assets/blue-heeler.png",
      "isFavorite": false,
      "id": 32
    },
    {
      "name": "Cordelia",
      "description": "Something about this dog makes me feel not comfortable.",
      "image": "/assets/corgi.png",
      "isFavorite": false,
      "id": 33
    },
    {
      "name": "Blubber",
      "description": "She's sooooo fat!",
      "image": "/assets/chihuahua.avif",
      "isFavorite": false,
      "id": 34
    },
    {
      "name": "Maleficient",
      "description": "She's so evil it's not even funny.",
      "image": "/assets/corgi.png",
      "isFavorite": false,
      "id": 35
    },
    {
      "name": "Hayes",
      "description": "He's a cutie pie and I wouldn't trade him for the world!",
      "image": "/assets/boxer.jpeg",
      "isFavorite": false,
      "id": 36
    },
    {
      "name": "Reese's",
      "description": "I love chocolate so I named this dog after my favorite chocolate.",
      "image": "/assets/corgi.png",
      "isFavorite": false,
      "id": 37
    }
  ]
}